Metadata-Version: 1.1
Name: bayes-logistic
Version: 0.2.0
Summary: Bayesian Logistic Regression using Laplace approximations to the posterior.
Home-page: https://github.com/maxpoint/bayes_logistic
Author: MaxPoint Interactive, Inc.
Author-email: rob.haslinger@maxpoint.com
License: BSD
Keywords: bayes_logistic
Platform: UNKNOWN
Classifier: Development Status :: 4 - Beta
Classifier: Intended Audience :: Developers
Classifier: License :: OSI Approved :: BSD License
Classifier: Natural Language :: English
Classifier: Programming Language :: Python :: 2
Classifier: Programming Language :: Python :: 2.6
Classifier: Programming Language :: Python :: 2.7
Classifier: Programming Language :: Python :: 3
Classifier: Programming Language :: Python :: 3.3
Classifier: Programming Language :: Python :: 3.4
